{"mappings": [{"item": {"url": "aws-vault/", "title": "aws-vault"}, "tags": ["aws", "security"]}, {"item": {"url": "backup/", "title": "Automated backup"}, "tags": ["launchd", "mermaid", "rclone", "security"]}, {"item": {"url": "devpi/", "title": "devpi"}, "tags": ["launchd", "mermaid", "python"]}, {"item": {"url": "git/", "title": "Git"}, "tags": ["git", "shell"]}, {"item": {"url": "gnupg-key-management/", "title": "GnuPG key management"}, "tags": ["cryptography", "gnupg", "security"]}, {"item": {"url": "jupyterlab/", "title": "JupyterLab"}, "tags": ["launchd", "python", "taskfile"]}, {"item": {"url": "rclone/", "title": "Rclone"}, "tags": ["rclone", "security", "ssh"]}, {"item": {"url": "tar-ssh/", "title": "tar over SSH"}, "tags": ["shell", "ssh"]}, {"item": {"url": "tmux-env-var-sync/", "title": "tmux environment variable sync"}, "tags": ["shell", "ssh", "tmux"]}, {"item": {"url": "wsl/", "title": "Windows Subsystem for Linux"}, "tags": ["ssh", "windows"]}]}